LICENSE
MANIFEST.in
README.rst
setup.cfg
setup.py
cardano/__init__.py
cardano/address.py
cardano/block.py
cardano/cbits.pyx
cardano/chimeric_ledger.py
cardano/config.py
cardano/constants.py
cardano/integrity.py
cardano/logic.py
cardano/node.py
cardano/peers.py
cardano/random.py
cardano/retrieve.py
cardano/storage.py
cardano/transport.py
cardano/utils.py
cardano/wallet.py
cardano/conf/configuration.yaml
cardano/conf/mainnet-genesis.json
cardano/conf/testnet-genesis.json
cbits/README.rst
cbits/cryptonite_align.h
cbits/cryptonite_bitfn.h
cbits/cryptonite_chacha.c
cbits/cryptonite_chacha.h
cbits/cryptonite_pbkdf2.c
cbits/cryptonite_pbkdf2.h
cbits/cryptonite_poly1305.c
cbits/cryptonite_poly1305.h
cbits/cryptonite_sha1.c
cbits/cryptonite_sha1.h
cbits/cryptonite_sha256.c
cbits/cryptonite_sha256.h
cbits/cryptonite_sha512.c
cbits/cryptonite_sha512.h
cbits/encrypted_sign.c
cbits/hmac.h
cbits/ed25519/curve25519-donna-32bit.h
cbits/ed25519/curve25519-donna-64bit.h
cbits/ed25519/curve25519-donna-helpers.h
cbits/ed25519/ed25519-donna-32bit-sse2.h
cbits/ed25519/ed25519-donna-32bit-tables.h
cbits/ed25519/ed25519-donna-64bit-tables.h
cbits/ed25519/ed25519-donna-64bit-x86-32bit.h
cbits/ed25519/ed25519-donna-64bit-x86.h
cbits/ed25519/ed25519-donna-basepoint-table.h
cbits/ed25519/ed25519-donna-batchverify.h
cbits/ed25519/ed25519-donna-impl-base.h
cbits/ed25519/ed25519-donna-portable-identify.h
cbits/ed25519/ed25519-donna-portable.h
cbits/ed25519/ed25519-donna.h
cbits/ed25519/ed25519-hash.h
cbits/ed25519/ed25519-randombytes.h
cbits/ed25519/ed25519.c
cbits/ed25519/ed25519.h
cbits/ed25519/modm-donna-32bit.h
cbits/ed25519/modm-donna-64bit.h
python_cardano.egg-info/PKG-INFO
python_cardano.egg-info/SOURCES.txt
python_cardano.egg-info/dependency_links.txt
python_cardano.egg-info/requires.txt
python_cardano.egg-info/top_level.txt