Metadata-Version: 1.0
Name: python-cardano
Version: 1.0.1
Summary: implement Cardano blockchain project in python
Home-page: https://github.com/safeada/python-cardano
Author: huangyi
Author-email: yi.codeplayer@gmail.com
License: MIT
Platform: OS Independent
